repositoryIntelligence.py
repositoryintelligence-1.0.11.dist-info/licenses/LICENSE
repositoryintelligence-1.0.11.dist-info/METADATA
repositoryintelligence-1.0.11.dist-info/WHEEL
repositoryintelligence-1.0.11.dist-info/top_level.txt
repositoryintelligence-1.0.11.dist-info/RECORD
