Metadata-Version: 2.4
Name: repositoryIntelligence
Version: 1.0.11
Summary: A package supporting analysis of DataCite Repositories.
Author-email: Ted Habermann <ted@metadatagamechangers.com>
Project-URL: Homepage, https://github.com/Metadata-Game-Changers/repositoryIntelligence
Project-URL: Bug Tracker, https://github.com/Metadata-Game-Changers/repositoryIntelligence/issues
Classifier: Programming Language :: Python :: 3
Classifier: License :: Free for non-commercial use
Classifier: Operating System :: OS Independent
Requires-Python: >=3.9
License-File: LICENSE
Requires-Dist: jsonpath_ng==1.7.0
Dynamic: license-file
